{
  "db": {
    "name": "db",
    "connector": "memory"
  },
  "mysql": {
    "host": "localhost",
    "port": 3306,
    "url": "",
    "database": "eventmanager",
    "password": "v9XahvutwDdVO6nB",
    "name": "mysql",
    "user": "eventmanager",
    "connector": "mysql"
  },
  "mailDS": {
    "name": "mailDS",
    "connector": "mail",
    "transports": [
      {
        "type": "smtp",
        "host": "authsmtp.securemail.pro",
        "secure": true,
        "port": 465,
        "tls": {
          "rejectUnauthorized": false
        },
        "auth": {
          "user": "info@stdout.it",
          "pass": "1cascox2"
        }
      }
    ]
  }
}
